{
  "project_info": {
    "project_number": "354224854914",
    "firebase_url": "https://policy-8d2cd.firebaseio.com",
    "project_id": "policy-8d2cd",
    "storage_bucket": "policy-8d2cd.appspot.com"
  },
  "client": [
    {
      "client_info": {
        "mobilesdk_app_id": "1:354224854914:android:2d85af107c0b15c080619b",
        "android_client_info": {
          "package_name": "com.itmit.policy.app"
        }
      },
      "oauth_client": [
        {
          "client_id": "354224854914-9upje3riq6cbdvstf9qk0jn506mkq7dj.apps.googleusercontent.com",
          "client_type": 3
        }
      ],
      "api_key": [
        {
          "current_key": "AIzaSyDXtQgcYj7_iIe3rEQ5QPjqPjcxWTRdZpg"
        }
      ],
      "services": {
        "appinvite_service": {
          "other_platform_oauth_client": [
            {
              "client_id": "354224854914-9upje3riq6cbdvstf9qk0jn506mkq7dj.apps.googleusercontent.com",
              "client_type": 3
            }
          ]
        }
      }
    }
  ],
  "configuration_version": "1"
}